COPYING
COPYING.LESSER
MANIFEST.in
NEWS.rst
README.rst
setup.cfg
setup.py
pywunderground/__init__.py
pywunderground/core.py
pywunderground/infos.py
pywunderground.egg-info/PKG-INFO
pywunderground.egg-info/SOURCES.txt
pywunderground.egg-info/dependency_links.txt
pywunderground.egg-info/requires.txt
pywunderground.egg-info/top_level.txt